{
  "s0_rotational_constant_a": 0.0219561,
  "s0_rotational_constant_b": 0.0258164,
  "s0_rotational_constant_c": 0.117092,
  "s1_rotational_constant_a": 0.0225534,
  "s1_rotational_constant_b": 0.0255904,
  "s1_rotational_constant_c": 0.1217087,
  "s0_rays_asymmetry_parameter": 0.9188466183638354,
  "s1_rays_asymmetry_parameter": 0.9387425583907265,
  "s0_volume": 850.51383,
  "s1_volume": 852.77031,
  "delta_volume": 2.2564800000000105,
  "s0_homo_lumo_gap": 0.9835581054484202,
  "s1_homo_lumo_gap": 0.6740640156841455,
  "delta_gap": -0.3094940897642746,
  "s0_dihedral_avg": -5.429684041911276,
  "s1_dihedral_avg": 4.466862094250593,
  "delta_dihedral": 9.89654613616187,
  "delta_dipole": null,
  "excitation_energy": "0.8760",
  "exciting_path_mean_volume": 851.518655,
  "s0_bonds_avg": 1.2590279211359756,
  "s1_bonds_avg": 1.28311528377061,
  "s0_angles_avg": 118.81894274883898,
  "s1_angles_avg": 117.99353806400356
}