{
  "charge": {
    "element": [
      "C",
      "C",
      "C",
      "N",
      "C",
      "C",
      "C",
      "C",
      "C",
      "C",
      "C",
      "C",
      "C",
      "N",
      "C",
      "C",
      "C",
      "C",
      "N",
      "C",
      "C",
      "C",
      "C",
      "C",
      "O",
      "C",
      "C",
      "Br",
      "H",
      "H",
      "H",
      "H",
      "H",
      "H",
      "H",
      "H",
      "H",
      "H",
      "H",
      "H",
      "H",
      "H",
      "H",
      "H",
      "H",
      "H",
      "H",
      "H",
      "H",
      "H",
      "H",
      "H"
    ],
    "charge_variation": [
      0.008256999999999987,
      -0.004589999999999999,
      0.014644999999999991,
      -0.04620099999999999,
      -0.007657999999999998,
      0.032738,
      -0.009600000000000001,
      0.020184000000000007,
      -0.00266799999999999,
      0.018012,
      0.02606,
      0.006128000000000022,
      0.03185399999999999,
      -0.024216000000000015,
      -0.01136799999999999,
      0.013937999999999992,
      -0.044265,
      -0.011768,
      0.07611499999999993,
      -0.004056999999999977,
      -0.0046760000000000135,
      -0.036248,
      -0.015736000000000007,
      0.019615999999999967,
      0.015675999999999912,
      0.022505999999999998,
      -0.02275900000000003,
      -0.07783499999999999,
      -0.0028779999999999986,
      0.003721000000000002,
      0.006784999999999999,
      0.0021870000000000014,
      0.002529,
      0.007882,
      0.0009100000000000011,
      0.008908,
      -0.005150999999999999,
      0.0008060000000000012,
      -0.00997,
      -5.999999999999062e-06,
      -0.002910999999999997,
      -0.003388,
      0.005301999999999999,
      -0.0009910000000000006,
      -0.0006239999999999996,
      -0.00317,
      0.0057,
      -0.0028369999999999992,
      -0.0007249999999999965,
      -0.0007920000000000149,
      -0.0070199999999999985,
      0.013648
    ]
  },
  "ground_state": {
    "HOMO-LUMO": 1.579427495254742,
    "charge": {
      "element": [
        "C",
        "C",
        "C",
        "N",
        "C",
        "C",
        "C",
        "C",
        "C",
        "C",
        "C",
        "C",
        "C",
        "N",
        "C",
        "C",
        "C",
        "C",
        "N",
        "C",
        "C",
        "C",
        "C",
        "C",
        "O",
        "C",
        "C",
        "Br",
        "H",
        "H",
        "H",
        "H",
        "H",
        "H",
        "H",
        "H",
        "H",
        "H",
        "H",
        "H",
        "H",
        "H",
        "H",
        "H",
        "H",
        "H",
        "H",
        "H",
        "H",
        "H",
        "H",
        "H"
      ],
      "charge": [
        -0.147949,
        -0.008292,
        0.233156,
        -0.184067,
        0.244648,
        -0.099027,
        -0.007135,
        0.049135,
        0.102584,
        -0.141124,
        -0.014799,
        -0.142219,
        0.446426,
        -0.855973,
        0.378583,
        -0.101241,
        -0.154636,
        0.413292,
        -0.666542,
        0.239443,
        0.239824,
        -0.155575,
        -0.057982,
        0.58968,
        -0.566861,
        -0.209573,
        0.350314,
        -0.82796,
        0.030729,
        0.058539,
        0.095375,
        0.017473,
        -0.008489,
        0.024056,
        0.0436,
        0.044479,
        0.032748,
        0.026701,
        0.011061,
        0.033033,
        0.040267,
        0.00573,
        -0.00947,
        0.013205,
        0.014412,
        0.004981,
        -0.00903,
        0.042032,
        0.040802,
        0.40199,
        0.052917,
        0.04673
      ]
    },
    "structure": {
      "bonds": 1.6598270705025862,
      "angles": 104.68856691253795,
      "DA": 94.91740740051075
    },
    "rotational_constant": {
      "A": 0.0391149,
      "B": 0.0398776,
      "C": 0.4887214
    },
    "rays_asymmetry_parameter": 0.9966072554556039,
    "volume": 571.93648
  },
  "excited_state": {
    "HOMO-LUMO": 0.08621109886766609,
    "charge": {
      "element": [
        "C",
        "C",
        "C",
        "N",
        "C",
        "C",
        "C",
        "C",
        "C",
        "C",
        "C",
        "C",
        "C",
        "N",
        "C",
        "C",
        "C",
        "C",
        "N",
        "C",
        "C",
        "C",
        "C",
        "C",
        "O",
        "C",
        "C",
        "Br",
        "H",
        "H",
        "H",
        "H",
        "H",
        "H",
        "H",
        "H",
        "H",
        "H",
        "H",
        "H",
        "H",
        "H",
        "H",
        "H",
        "H",
        "H",
        "H",
        "H",
        "H",
        "H",
        "H",
        "H"
      ],
      "charge": [
        -0.139692,
        -0.012882,
        0.247801,
        -0.230268,
        0.23699,
        -0.066289,
        -0.016735,
        0.069319,
        0.099916,
        -0.123112,
        0.011261,
        -0.136091,
        0.47828,
        -0.880189,
        0.367215,
        -0.087303,
        -0.198901,
        0.401524,
        -0.590427,
        0.235386,
        0.235148,
        -0.191823,
        -0.073718,
        0.609296,
        -0.551185,
        -0.187067,
        0.327555,
        -0.905795,
        0.027851,
        0.06226,
        0.10216,
        0.01966,
        -0.00596,
        0.031938,
        0.04451,
        0.053387,
        0.027597,
        0.027507,
        0.001091,
        0.033027,
        0.037356,
        0.002342,
        -0.004168,
        0.012214,
        0.013788,
        0.001811,
        -0.00333,
        0.039195,
        0.040077,
        0.401198,
        0.045897,
        0.060378
      ]
    },
    "structure": {
      "bonds": 1.3369775024866073,
      "angles": 114.54756927714912,
      "DA": 90.14979947752771
    },
    "rotational_constant": {
      "A": 0.0439146,
      "B": 0.0466615,
      "C": 0.4120981
    },
    "rays_asymmetry_parameter": 0.9850786360605513,
    "excited_energy": "0.0992",
    "volume": 577.67895
  },
  "exciting_path_mean_volume": 573.2903600000001
}