{
  "s0_rotational_constant_a": 0.0495484,
  "s0_rotational_constant_b": 0.0523999,
  "s0_rotational_constant_c": 0.8791877,
  "s1_rotational_constant_a": 0.0500368,
  "s1_rotational_constant_b": 0.0521251,
  "s1_rotational_constant_c": 0.9382792,
  "s0_rays_asymmetry_parameter": 0.9931259283401837,
  "s1_rays_asymmetry_parameter": 0.9952979051664276,
  "s0_volume": 515.22812,
  "s1_volume": 519.11386,
  "delta_volume": 3.8857400000000553,
  "s0_homo_lumo_gap": 0.916892941912061,
  "s1_homo_lumo_gap": 0.0652147969024206,
  "delta_gap": -0.8516781450096405,
  "s0_dihedral_avg": -8.01151537847632,
  "s1_dihedral_avg": -1.076367722183043,
  "delta_dihedral": 6.935147656293276,
  "delta_dipole": null,
  "excitation_energy": "0.0916",
  "exciting_path_mean_volume": 516.7670766666666,
  "s0_bonds_avg": 1.2562235463338,
  "s1_bonds_avg": 1.2613079847852,
  "s0_angles_avg": 118.37588936468224,
  "s1_angles_avg": 118.41861664416062
}