{
  "s0_rotational_constant_a": 0.0206508,
  "s0_rotational_constant_b": 0.022067,
  "s0_rotational_constant_c": 0.1644352,
  "s1_rotational_constant_a": 0.0207696,
  "s1_rotational_constant_b": 0.0220608,
  "s1_rotational_constant_c": 0.1623467,
  "s0_rays_asymmetry_parameter": 0.9803010618676296,
  "s1_rays_asymmetry_parameter": 0.9817597619954076,
  "s0_volume": 830.81394,
  "s1_volume": 828.17149,
  "delta_volume": -2.6424500000000535,
  "s0_homo_lumo_gap": 1.328135829380388,
  "s1_homo_lumo_gap": 0.8925523611604906,
  "delta_gap": -0.43558346821989735,
  "s0_dihedral_avg": 1.898335887088494,
  "s1_dihedral_avg": -11.526434369867792,
  "delta_dihedral": -13.424770256956286,
  "delta_dipole": null,
  "excitation_energy": "1.0656",
  "exciting_path_mean_volume": 829.0435033333333,
  "s0_bonds_avg": 1.290245040372683,
  "s1_bonds_avg": 1.2921205211012194,
  "s0_angles_avg": 119.53042126713783,
  "s1_angles_avg": 119.53089236576939
}